RandomGenerator.py
__init__.py
setup.py
RandomGenerator_Griff1235.egg-info/PKG-INFO
RandomGenerator_Griff1235.egg-info/SOURCES.txt
RandomGenerator_Griff1235.egg-info/dependency_links.txt
RandomGenerator_Griff1235.egg-info/top_level.txt